{
    "filename": "95.png",
    "name": "95.png",
    "id": "9248344",
    "mppx": "1.1781",
    "height": 1024,
    "loaded": 1500322,
    "ajaxToken": {},
    "position": {
        "offx": 0.6639239714040657,
        "offy": 0.29477768752572736,
        "zoom": 1.320733761178327
    },
    "stain": "",
    "roilist": [
        {
            "method": "spot",
            "radius": 2.546473134708429,
            "path": {
                "x": [
                    35.93411642351615
                ],
                "y": [
                    347.93944754373564
                ]
            },
            "id": "862094702"
        },
        {
            "method": "spot",
            "radius": 2.546473134708429,
            "path": {
                "x": [
                    48.76268457179851
                ],
                "y": [
                    337.51623592325615
                ]
            },
            "id": "227780227"
        },
        {
            "method": "spot",
            "radius": 2.546473134708429,
            "path": {
                "x": [
                    55.17696864593968
                ],
                "y": [
                    337.51623592325615
                ]
            },
            "id": "908291108"
        },
        {
            "method": "spot",
            "radius": 2.546473134708429,
            "path": {
                "x": [
                    51.9698266088691
                ],
                "y": [
                    323.8858822657062
                ]
            },
            "id": "826941252"
        },
        {
            "method": "spot",
            "radius": 2.546473134708429,
            "path": {
                "x": [
                    62.39303822934851
                ],
                "y": [
                    316.6698126822974
                ]
            },
            "id": "593702277"
        },
        {
            "method": "spot",
            "radius": 2.546473134708429,
            "path": {
                "x": [
                    81.63589045177204
                ],
                "y": [
                    303.0394590247474
                ]
            },
            "id": "975688545"
        },
        {
            "method": "spot",
            "radius": 2.546473134708429,
            "path": {
                "x": [
                    87.24838901664558
                ],
                "y": [
                    286.2019633301268
                ]
            },
            "id": "154804502"
        },
        {
            "method": "spot",
            "radius": 2.546473134708429,
            "path": {
                "x": [
                    706.2268021712696
                ],
                "y": [
                    232.48233420919428
                ]
            },
            "id": "401053633"
        },
        {
            "method": "spot",
            "radius": 2.546473134708429,
            "path": {
                "x": [
                    788.0089241165697
                ],
                "y": [
                    198.80734281995305
                ]
            },
            "id": "064423718"
        },
        {
            "method": "spot",
            "radius": 2.546473134708429,
            "path": {
                "x": [
                    763.1535733292726
                ],
                "y": [
                    235.68947624626486
                ]
            },
            "id": "522523158"
        },
        {
            "method": "spot",
            "radius": 2.546473134708429,
            "path": {
                "x": [
                    759.946431292202
                ],
                "y": [
                    251.72518643161783
                ]
            },
            "id": "155714714"
        },
        {
            "method": "spot",
            "radius": 2.546473134708429,
            "path": {
                "x": [
                    770.3696429126815
                ],
                "y": [
                    256.5358994872237
                ]
            },
            "id": "990943714"
        },
        {
            "method": "spot",
            "radius": 2.546473134708429,
            "path": {
                "x": [
                    754.3339327273284
                ],
                "y": [
                    271.76982416330895
                ]
            },
            "id": "232989774"
        },
        {
            "method": "spot",
            "radius": 2.546473134708429,
            "path": {
                "x": [
                    767.9642863848785
                ],
                "y": [
                    275.7787517096472
                ]
            },
            "id": "394936279"
        },
        {
            "method": "spot",
            "color": "yellow",
            "radius": 2.546473134708429,
            "path": {
                "x": [
                    705,
                    707,
                    710,
                    707
                ],
                "y": [
                    319,
                    317,
                    319,
                    322
                ]
            },
            "id": "487996832"
        },
        {
            "method": "spot",
            "radius": 2.546473134708429,
            "path": {
                "x": [
                    843.3321242560373
                ],
                "y": [
                    55.28773666104422
                ]
            },
            "id": "748155909"
        },
        {
            "method": "spot",
            "radius": 2.546473134708429,
            "path": {
                "x": [
                    819.2785589780078
                ],
                "y": [
                    36.04488443862068
                ]
            },
            "id": "114370926"
        },
        {
            "method": "spot",
            "radius": 2.546473134708429,
            "path": {
                "x": [
                    788.0089241165697
                ],
                "y": [
                    29.630600364479495
                ]
            },
            "id": "798204115"
        },
        {
            "method": "spot",
            "radius": 2.546473134708429,
            "path": {
                "x": [
                    755.1357182365962
                ],
                "y": [
                    77.73773092053834
                ]
            },
            "id": "931411295"
        },
        {
            "method": "spot",
            "radius": 2.546473134708429,
            "path": {
                "x": [
                    748.721434162455
                ],
                "y": [
                    85.75558601321481
                ]
            },
            "id": "400316866"
        },
        {
            "method": "spot",
            "radius": 2.546473134708429,
            "path": {
                "x": [
                    545.8697003177401
                ],
                "y": [
                    151.5019977731619
                ]
            },
            "id": "265151238"
        },
        {
            "method": "spot",
            "radius": 2.546473134708429,
            "path": {
                "x": [
                    630.0571787908432
                ],
                "y": [
                    368.7858707846943
                ]
            },
            "id": "550523360"
        },
        {
            "method": "spot",
            "radius": 2.546473134708429,
            "path": {
                "x": [
                    639.678604902055
                ],
                "y": [
                    362.3715867105532
                ]
            },
            "id": "141403307"
        },
        {
            "method": "spot",
            "radius": 2.546473134708429,
            "path": {
                "x": [
                    878.6106866638137
                ],
                "y": [
                    309.4537430988884
                ]
            },
            "id": "627796773"
        },
        {
            "method": "spot",
            "radius": 2.546473134708429,
            "path": {
                "x": [
                    981.2392318500727
                ],
                "y": [
                    149.09664124535894
                ]
            },
            "id": "255428406"
        },
        {
            "method": "spot",
            "radius": 2.546473134708429,
            "path": {
                "x": [
                    974.8249477759315
                ],
                "y": [
                    153.9073543009648
                ]
            },
            "id": "017564165"
        },
        {
            "method": "spot",
            "radius": 2.546473134708429,
            "path": {
                "x": [
                    970.0142347203255
                ],
                "y": [
                    170.7448499955854
                ]
            },
            "id": "778736175"
        },
        {
            "method": "spot",
            "radius": 2.546473134708429,
            "path": {
                "x": [
                    957.1856665720431
                ],
                "y": [
                    155.5109253195001
                ]
            },
            "id": "341558406"
        },
        {
            "method": "spot",
            "radius": 2.546473134708429,
            "path": {
                "x": [
                    766.3607153663431
                ],
                "y": [
                    53.68416564250892
                ]
            },
            "id": "224503238"
        },
        {
            "method": "spot",
            "radius": 2.546473134708429,
            "path": {
                "x": [
                    812.0624893945991
                ],
                "y": [
                    28.828814855211853
                ]
            },
            "id": "882879799"
        },
        {
            "method": "spot",
            "radius": 2.546473134708429,
            "path": {
                "x": [
                    759.946431292202
                ],
                "y": [
                    105.80022374490599
                ]
            },
            "id": "690126826"
        },
        {
            "method": "spot",
            "radius": 2.546473134708429,
            "path": {
                "x": [
                    757.541074764399
                ],
                "y": [
                    94.57522661515893
                ]
            },
            "id": "163836298"
        },
        {
            "method": "spot",
            "radius": 2.546473134708429,
            "path": {
                "x": [
                    807.2517763389931
                ],
                "y": [
                    150.70021226389423
                ]
            },
            "id": "000673365"
        },
        {
            "method": "spot",
            "radius": 2.546473134708429,
            "path": {
                "x": [
                    829.7017705984873
                ],
                "y": [
                    159.51985286583835
                ]
            },
            "id": "056640285"
        },
        {
            "method": "spot",
            "radius": 2.546473134708429,
            "path": {
                "x": [
                    835.3142691633609
                ],
                "y": [
                    151.5019977731619
                ]
            },
            "id": "073378695"
        },
        {
            "method": "spot",
            "radius": 2.546473134708429,
            "path": {
                "x": [
                    817.6749879594726
                ],
                "y": [
                    202.01448485702366
                ]
            },
            "id": "525056791"
        },
        {
            "method": "spot",
            "radius": 2.546473134708429,
            "path": {
                "x": [
                    811.2607038853314
                ],
                "y": [
                    198.80734281995305
                ]
            },
            "id": "908161936"
        },
        {
            "method": "spot",
            "radius": 2.546473134708429,
            "path": {
                "x": [
                    809.6571328667961
                ],
                "y": [
                    185.9787746716707
                ]
            },
            "id": "087139384"
        },
        {
            "method": "spot",
            "radius": 2.546473134708429,
            "path": {
                "x": [
                    825.692843052149
                ],
                "y": [
                    196.4019862921501
                ]
            },
            "id": "202359557"
        },
        {
            "method": "spot",
            "radius": 2.546473134708429,
            "path": {
                "x": [
                    810.4589183760637
                ],
                "y": [
                    295.0216039320708
                ]
            },
            "id": "186297421"
        },
        {
            "method": "spot",
            "color": "yellow",
            "radius": 2.546473134708429,
            "path": {
                "x": [
                    867,
                    869,
                    872,
                    869
                ],
                "y": [
                    274,
                    271,
                    274,
                    276
                ]
            },
            "id": "278550428"
        },
        {
            "method": "spot",
            "radius": 2.546473134708429,
            "path": {
                "x": [
                    853.7553358765166
                ],
                "y": [
                    272.57160967257664
                ]
            },
            "id": "855465733"
        },
        {
            "method": "spot",
            "radius": 2.546473134708429,
            "path": {
                "x": [
                    861.7731909691933
                ],
                "y": [
                    261.3466125428296
                ]
            },
            "id": "846866640"
        },
        {
            "method": "spot",
            "radius": 2.546473134708429,
            "path": {
                "x": [
                    858.5660489321226
                ],
                "y": [
                    255.73411397795604
                ]
            },
            "id": "268283757"
        },
        {
            "method": "spot",
            "radius": 2.546473134708429,
            "path": {
                "x": [
                    851.3499793487138
                ],
                "y": [
                    250.12161541308254
                ]
            },
            "id": "391801592"
        },
        {
            "method": "spot",
            "radius": 2.546473134708429,
            "path": {
                "x": [
                    840.1249822189668
                ],
                "y": [
                    238.89661828333547
                ]
            },
            "id": "395550402"
        },
        {
            "method": "spot",
            "radius": 2.546473134708429,
            "path": {
                "x": [
                    843.3321242560373
                ],
                "y": [
                    219.65376606091192
                ]
            },
            "id": "794252728"
        },
        {
            "method": "spot",
            "radius": 2.546473134708429,
            "path": {
                "x": [
                    851.3499793487138
                ],
                "y": [
                    214.84305300530602
                ]
            },
            "id": "859809809"
        },
        {
            "method": "spot",
            "radius": 2.546473134708429,
            "path": {
                "x": [
                    847.3410518023755
                ],
                "y": [
                    230.07697768139133
                ]
            },
            "id": "628228511"
        },
        {
            "method": "spot",
            "radius": 2.546473134708429,
            "path": {
                "x": [
                    853.7553358765166
                ],
                "y": [
                    239.6984037926031
                ]
            },
            "id": "940118139"
        },
        {
            "method": "spot",
            "radius": 2.546473134708429,
            "path": {
                "x": [
                    864.1785474969961
                ],
                "y": [
                    236.4912617555325
                ]
            },
            "id": "415676263"
        },
        {
            "method": "spot",
            "radius": 2.546473134708429,
            "path": {
                "x": [
                    867.3856895340667
                ],
                "y": [
                    247.71625888527956
                ]
            },
            "id": "212166628"
        },
        {
            "method": "spot",
            "color": "yellow",
            "radius": 2.546473134708429,
            "path": {
                "x": [
                    867,
                    869,
                    872,
                    869
                ],
                "y": [
                    258,
                    256,
                    258,
                    261
                ]
            },
            "id": "207752395"
        },
        {
            "method": "spot",
            "radius": 2.546473134708429,
            "path": {
                "x": [
                    860.169619950658
                ],
                "y": [
                    228.47340666285604
                ]
            },
            "id": "336194793"
        },
        {
            "method": "spot",
            "radius": 2.546473134708429,
            "path": {
                "x": [
                    643.3411611083897
                ],
                "y": [
                    452.1651494644554
                ]
            },
            "id": "727752309"
        },
        {
            "method": "spot",
            "radius": 2.546473134708429,
            "path": {
                "x": [
                    639.3322335620514
                ],
                "y": [
                    444.9490798810466
                ]
            },
            "id": "573779045"
        },
        {
            "method": "spot",
            "radius": 2.546473134708429,
            "path": {
                "x": [
                    804.8849055156355
                ],
                "y": [
                    293.1550472664956
                ]
            },
            "id": "015213152"
        },
        {
            "method": "spot",
            "radius": 2.546473134708429,
            "path": {
                "x": [
                    780.4945903237134
                ],
                "y": [
                    45.45143203334872
                ]
            },
            "id": "889399701"
        },
        {
            "method": "spot",
            "radius": 2.546473134708429,
            "path": {
                "x": [
                    770.3119143560142
                ],
                "y": [
                    86.93046904612893
                ]
            },
            "id": "512085603"
        },
        {
            "method": "spot",
            "radius": 2.546473134708429,
            "path": {
                "x": [
                    770.3119143560142
                ],
                "y": [
                    82.11975599052305
                ]
            },
            "id": "675441956"
        },
        {
            "method": "spot",
            "radius": 2.546473134708429,
            "path": {
                "x": [
                    510.53340935329663
                ],
                "y": [
                    143.8572402041319
                ]
            },
            "id": "239437350"
        },
        {
            "method": "spot",
            "radius": 2.546473134708429,
            "path": {
                "x": [
                    767.9065578282114
                ],
                "y": [
                    263.32328108501133
                ]
            },
            "id": "632568262"
        },
        {
            "method": "spot",
            "radius": 2.546473134708429,
            "path": {
                "x": [
                    845.6797522271734
                ],
                "y": [
                    207.19829543627603
                ]
            },
            "id": "271044713"
        }
    ],
    "state": 1,
    "ki67": {
        "airesult": {},
        "result": []
    },
    "total": 1500322,
    "toolType": "ki67ann",
    "mppy": "1.1781",
    "width": 1024
}